{
    "name": "Dignus Orb",
    "rarity": 5,
    "exclusive": [
        "mage"
    ],
    "loreDescription": [
        "\"Whenever times are hard, I just look up to the sky, and it shows me the way forward.\""
    ],
    "skillDescription": {
        "base": "Grants a barrier equivalent to 60.0% of Attack for 2 turns when caster uses a non-attack skill.",
        "max": "Grants a barrier equivalent to 120.0% of Attack for 2 turns when caster uses a non-attack skill."
    },
    "stats": {
        "base": {
            "atk": 21,
            "hp": 32
        },
        "max": {
            "atk": 273,
            "hp": 416
        }
    }
}
