{
    "gameId": "c2002",
    "name": "Fallen Cecilia",
    "rarity": 5,
    "classType": "knight",
    "element": "dark",
    "zodiac": "sagittarius",
    "specialtyChangeName": "",
    "selfSkillBarName": "",
    "background": "Fallen Cecilia is chasing a mage who turned her family into dark magic stones, dreaming of the day she can get her revenge and join her loved ones again.",
    "relations": [
        {
            "hero": "luna",
            "relationType": "hostile"
        },
        {
            "hero": "cecilia",
            "relationType": "friendly"
        }
    ],
    "stats": {
        "lv1BaseStarNoAwaken": {
            "cp": 1414,
            "atk": 74,
            "hp": 353,
            "spd": 98,
            "def": 82,
            "chc": 0.15,
            "chd": 1.5,
            "eff": 0,
            "efr": 0,
            "dac": 0.05
        },
        "lv50FiveStarNoAwaken": {
            "cp": 12001,
            "atk": 596,
            "hp": 4685,
            "spd": 98,
            "def": 528,
            "chc": 0.15,
            "chd": 1.5,
            "eff": 0,
            "efr": 0,
            "dac": 0.05
        },
        "lv50FiveStarFullyAwakened": {
            "cp": 13591,
            "atk": 716,
            "hp": 5446,
            "spd": 100,
            "def": 559,
            "chc": 0.15,
            "chd": 1.5,
            "eff": 0,
            "efr": 0,
            "dac": 0.05
        },
        "lv60SixStarNoAwaken": {
            "cp": 14985,
            "atk": 744,
            "hp": 5890,
            "spd": 98,
            "def": 655,
            "chc": 0.15,
            "chd": 1.5,
            "eff": 0,
            "efr": 0,
            "dac": 0.05
        },
        "lv60SixStarFullyAwakened": {
            "cp": 17114,
            "atk": 894,
            "hp": 6840,
            "spd": 104,
            "def": 694,
            "chc": 0.15,
            "chd": 1.5,
            "eff": 0,
            "efr": 0,
            "dac": 0.05
        }
    },
    "skills": [
        {
            "isPassive": false,
            "soulBurn": 0,
            "selfSkillBarValue": 0,
            "soulBurnEffect": "",
            "awakenUpgrade": false,
            "cooldown": 0,
            "name": "Mistake",
            "soulAcquire": 1,
            "description": "Attacks with a spear of revenge, with a 85% chance to provoke for 1 turn. Damage dealt increases proportional to the caster's max Health.",
            "enhancement": [
                {
                    "description": "+5% damage dealt",
                    "resources": [
                        {
                            "item": "gold",
                            "qty": 4000
                        },
                        {
                            "item": "molagora",
                            "qty": 1
                        }
                    ]
                },
                {
                    "description": "+5% effect chance",
                    "resources": [
                        {
                            "item": "gold",
                            "qty": 8000
                        },
                        {
                            "item": "molagora",
                            "qty": 2
                        }
                    ]
                },
                {
                    "description": "+10% damage dealt",
                    "resources": [
                        {
                            "item": "gold",
                            "qty": 33000
                        },
                        {
                            "item": "molagora",
                            "qty": 2
                        },
                        {
                            "item": "archers-vision",
                            "qty": 5
                        }
                    ]
                },
                {
                    "description": "+10% effect chance",
                    "resources": [
                        {
                            "item": "gold",
                            "qty": 47000
                        },
                        {
                            "item": "molagora",
                            "qty": 3
                        },
                        {
                            "item": "archers-vision",
                            "qty": 7
                        }
                    ]
                },
                {
                    "description": "+15% damage dealt",
                    "resources": [
                        {
                            "item": "gold",
                            "qty": 84000
                        },
                        {
                            "item": "molagora",
                            "qty": 6
                        },
                        {
                            "item": "mercenarys-medicine",
                            "qty": 2
                        }
                    ]
                }
            ],
            "buffs": [],
            "debuffs": [
                "stic_provoke"
            ],
            "damageModifiers": [
                {
                    "name": "pow",
                    "value": 1,
                    "soulburn": 1
                },
                {
                    "name": "atk_rate",
                    "value": 0.7,
                    "soulburn": 0.7
                },
                {
                    "name": "hp_rate",
                    "value": 0.07,
                    "soulburn": 0.07
                }
            ],
            "simpleDmgMod": {
                "description": "((atk_rate * hero_atk) + (hp_rate * hero_hp)) * pow! * constant",
                "value": "((0.7 * hero_atk) + (0.07 * hero_hp)) * 1.0 * 1.871",
                "simplified": "((1.3097 * hero_atk) + (0.131 * hero_hp))",
                "soulburn": "((0.7 * hero_atk) + (0.07 * hero_hp)) * 1.0 * 1.871",
                "simplifiedSoulburn": "((1.3097 * hero_atk) + (0.131 * hero_hp))"
            }
        },
        {
            "isPassive": true,
            "soulBurn": 0,
            "selfSkillBarValue": 0,
            "soulBurnEffect": "",
            "awakenUpgrade": true,
            "cooldown": 0,
            "name": "Strong Instinct",
            "soulAcquire": 0,
            "description": "Grants a barrier for 2 turns to all allies at the start of the battle, and grants a barrier for 2 turns to the ally with the lowest Health at the end of the caster's turn. Barrier strength increases proportional to the caster's max Health.",
            "enhancement": [
                {
                    "description": "+5% barrier strength",
                    "resources": [
                        {
                            "item": "gold",
                            "qty": 4000
                        },
                        {
                            "item": "molagora",
                            "qty": 1
                        }
                    ]
                },
                {
                    "description": "+10% barrier strength",
                    "resources": [
                        {
                            "item": "gold",
                            "qty": 8000
                        },
                        {
                            "item": "molagora",
                            "qty": 2
                        }
                    ]
                },
                {
                    "description": "+10% barrier strength",
                    "resources": [
                        {
                            "item": "gold",
                            "qty": 33000
                        },
                        {
                            "item": "molagora",
                            "qty": 2
                        },
                        {
                            "item": "archers-vision",
                            "qty": 5
                        }
                    ]
                },
                {
                    "description": "+10% barrier strength",
                    "resources": [
                        {
                            "item": "gold",
                            "qty": 47000
                        },
                        {
                            "item": "molagora",
                            "qty": 3
                        },
                        {
                            "item": "archers-vision",
                            "qty": 7
                        }
                    ]
                },
                {
                    "description": "+15% barrier strength",
                    "resources": [
                        {
                            "item": "gold",
                            "qty": 84000
                        },
                        {
                            "item": "molagora",
                            "qty": 6
                        },
                        {
                            "item": "mercenarys-medicine",
                            "qty": 2
                        }
                    ]
                }
            ],
            "buffs": [
                "stic_protect"
            ],
            "debuffs": [],
            "damageModifiers": [
                {
                    "name": "pow",
                    "value": 0,
                    "soulburn": 0
                },
                {
                    "name": "atk_rate",
                    "value": 0,
                    "soulburn": 0
                }
            ],
            "simpleDmgMod": {
                "description": "",
                "value": "",
                "simplified": "",
                "soulburn": "",
                "simplifiedSoulburn": ""
            }
        },
        {
            "isPassive": false,
            "soulBurn": 20,
            "selfSkillBarValue": 0,
            "soulBurnEffect": "Skill cooldown is decreased by 2 turns.",
            "awakenUpgrade": false,
            "cooldown": 6,
            "name": "Spear of Resentment",
            "soulAcquire": 2,
            "description": "Attacks all enemies in an explosion of spiteful emotions. Grants all allies Skill Nullifier, negating damage received from the next skill attack. Damage dealt increases proportional to the caster's max Health.",
            "enhancement": [
                {
                    "description": "+5% damage dealt",
                    "resources": [
                        {
                            "item": "gold",
                            "qty": 4000
                        },
                        {
                            "item": "molagora",
                            "qty": 1
                        }
                    ]
                },
                {
                    "description": "+5% damage dealt",
                    "resources": [
                        {
                            "item": "gold",
                            "qty": 8000
                        },
                        {
                            "item": "molagora",
                            "qty": 2
                        }
                    ]
                },
                {
                    "description": "-1 turn cooldown",
                    "resources": [
                        {
                            "item": "gold",
                            "qty": 33000
                        },
                        {
                            "item": "molagora",
                            "qty": 2
                        },
                        {
                            "item": "archers-vision",
                            "qty": 5
                        }
                    ]
                },
                {
                    "description": "+10% damage dealt",
                    "resources": [
                        {
                            "item": "gold",
                            "qty": 47000
                        },
                        {
                            "item": "molagora",
                            "qty": 3
                        },
                        {
                            "item": "archers-vision",
                            "qty": 7
                        }
                    ]
                },
                {
                    "description": "+15% damage dealt",
                    "resources": [
                        {
                            "item": "gold",
                            "qty": 84000
                        },
                        {
                            "item": "molagora",
                            "qty": 6
                        },
                        {
                            "item": "mercenarys-medicine",
                            "qty": 2
                        }
                    ]
                }
            ],
            "buffs": [
                "stic_endure"
            ],
            "debuffs": [],
            "damageModifiers": [
                {
                    "name": "pow",
                    "value": 0.95,
                    "soulburn": 0.95
                },
                {
                    "name": "atk_rate",
                    "value": 0.65,
                    "soulburn": 0.65
                },
                {
                    "name": "hp_rate",
                    "value": 0.12,
                    "soulburn": 0.12
                }
            ],
            "simpleDmgMod": {
                "description": "((atk_rate * hero_atk) + (hp_rate * hero_hp)) * pow! * constant",
                "value": "((0.65 * hero_atk) + (0.12 * hero_hp)) * 0.95 * 1.871",
                "simplified": "((1.1553 * hero_atk) + (0.2133 * hero_hp))",
                "soulburn": "((0.65 * hero_atk) + (0.12 * hero_hp)) * 0.95 * 1.871",
                "simplifiedSoulburn": "((1.1553 * hero_atk) + (0.2133 * hero_hp))"
            }
        }
    ],
    "specialtySkill": {
        "name": "An Indelible Duty",
        "description": "Though a dark magic stone has caused part of her body to harden into stone and is destroying her mind, she refuses to put her weapon down.",
        "dispatch": "[Battle] Type",
        "enhancement": "Reward Bonus +6%",
        "stats": {
            "command": 89,
            "charm": 95,
            "politics": 59
        }
    },
    "camping": {
        "options": [
            "horror-story",
            "food-story"
        ],
        "reactions": {
            "advice": -4,
            "belief": 8,
            "bizarre-story": -2,
            "comforting-cheer": -5,
            "complain": -5,
            "criticism": 6,
            "cute-cheer": 3,
            "dream": 5,
            "food-story": 2,
            "gossip": -3,
            "happy-memory": 1,
            "heroic-cheer": 3,
            "heroic-tale": 3,
            "horror-story": 0,
            "interesting-story": 2,
            "joyful-memory": 4,
            "myth": 4,
            "occult": 5,
            "reality-check": -3,
            "sad-memory": 2,
            "self-indulgent": 3,
            "unique-comment": 4
        }
    },
    "memoryImprintFormation": {
        "north": true,
        "south": true,
        "east": true,
        "west": true
    },
    "memoryImprintAttribute": "efr",
    "memoryImprint": [
        {
            "rank": "d",
            "status": {
                "type": "efr",
                "increase": 0
            }
        },
        {
            "rank": "c",
            "status": {
                "type": "efr",
                "increase": 0
            }
        },
        {
            "rank": "b",
            "status": {
                "type": "efr",
                "increase": 0.048
            }
        },
        {
            "rank": "a",
            "status": {
                "type": "efr",
                "increase": 0.072
            }
        },
        {
            "rank": "s",
            "status": {
                "type": "efr",
                "increase": 0.096
            }
        },
        {
            "rank": "ss",
            "status": {
                "type": "efr",
                "increase": 0.12
            }
        },
        {
            "rank": "sss",
            "status": {
                "type": "efr",
                "increase": 0.144
            }
        }
    ],
    "awakening": [
        {
            "rank": 1,
            "skillUpgrade": false,
            "statsIncrease": [
                {
                    "hp": 0.03
                },
                {
                    "atk": 20
                },
                {
                    "hp": 60
                }
            ],
            "resources": [
                {
                    "item": "dark-rune",
                    "qty": 10
                }
            ]
        },
        {
            "rank": 2,
            "skillUpgrade": false,
            "statsIncrease": [
                {
                    "spd": 2
                },
                {
                    "atk": 20
                },
                {
                    "hp": 60
                }
            ],
            "resources": [
                {
                    "item": "dark-rune",
                    "qty": 15
                },
                {
                    "item": "greater-dark-rune",
                    "qty": 2
                }
            ]
        },
        {
            "rank": 3,
            "skillUpgrade": true,
            "statsIncrease": [
                {
                    "atk": 20
                },
                {
                    "hp": 60
                }
            ],
            "resources": [
                {
                    "item": "dark-rune",
                    "qty": 20
                },
                {
                    "item": "greater-dark-rune",
                    "qty": 10
                }
            ]
        },
        {
            "rank": 4,
            "skillUpgrade": false,
            "statsIncrease": [
                {
                    "def": 0.06
                },
                {
                    "atk": 30
                },
                {
                    "hp": 80
                }
            ],
            "resources": [
                {
                    "item": "greater-dark-rune",
                    "qty": 10
                },
                {
                    "item": "epic-dark-rune",
                    "qty": 2
                }
            ]
        },
        {
            "rank": 5,
            "skillUpgrade": false,
            "statsIncrease": [
                {
                    "hp": 0.06
                },
                {
                    "atk": 30
                },
                {
                    "hp": 80
                }
            ],
            "resources": [
                {
                    "item": "epic-dark-rune",
                    "qty": 6
                },
                {
                    "item": "cold-look",
                    "qty": 15
                }
            ]
        },
        {
            "rank": 6,
            "skillUpgrade": false,
            "statsIncrease": [
                {
                    "spd": 4
                },
                {
                    "atk": 30
                },
                {
                    "hp": 80
                }
            ],
            "resources": [
                {
                    "item": "epic-dark-rune",
                    "qty": 10
                },
                {
                    "item": "mercenarys-medicine",
                    "qty": 10
                }
            ]
        }
    ],
    "summonQuote": "Are you someone whom I can trust?",
    "description": "A dark dragon bound by a desire for revenge and an endless grudge"
}
